eflowpy/__init__.py
eflowpy/core.py
eflowpy/hydraulic/__init__.py
eflowpy/hydrological/__init__.py
eflowpy/hydrological/base.py
eflowpy/hydrological/fdc.py
eflowpy/hydrological/gefc.py
eflowpy/hydrological/sevenq10.py
eflowpy/hydrological/tennant.py
eflowpy/hydrological/tessman.py
eflowpy/utils/__init__.py
eflowpy/utils/data_reader.py
eflowpy/utils/run_all.py
eflowpy-1.0.1.dist-info/licenses/LICENSE
eflowpy-1.0.1.dist-info/METADATA
eflowpy-1.0.1.dist-info/WHEEL
eflowpy-1.0.1.dist-info/top_level.txt
eflowpy-1.0.1.dist-info/RECORD
