Metadata-Version: 2.4
Name: eflowpy
Version: 1.0.1
Summary: A Python package for estimating environmental flow requirements using hydrological methods.
Home-page: https://github.com/gokhancuceloglu/eflowpy
Author: Gokhan Cuceloglu
Author-email: cuceloglugokhan@gmail.com
License: MIT
Classifier: Programming Language :: Python :: 3
Classifier: License :: OSI Approved :: MIT License
Classifier: Operating System :: OS Independent
Requires-Python: >=3.7
License-File: LICENSE
Requires-Dist: pandas
Requires-Dist: numpy
Requires-Dist: matplotlib
Requires-Dist: scipy
Dynamic: author
Dynamic: author-email
Dynamic: classifier
Dynamic: description
Dynamic: description-content-type
Dynamic: home-page
Dynamic: license
Dynamic: license-file
Dynamic: requires-dist
Dynamic: requires-python
Dynamic: summary
